sprinko/_cli/__main__.py
sprinko/_cli/bottle.py
sprinko/_cli/cache.py
sprinko/_cli/script.py
sprinko/_cli_bottler/__main__.py
sprinko/base/__init__.py
sprinko/base/caching.py
sprinko/base/env.py
sprinko/core/__init__.py
sprinko/core/bottle.py
sprinko/core/bowl.py
sprinko/core/ctx.py
sprinko/extra/dictionary.py
sprinko/extra/file.py
sprinko/extra/git.py
sprinko/extra/hashing.py
sprinko/extra/log.py
sprinko/extra/misc.py
sprinko/extra/object.py
sprinko/extra/prompt.py
sprinko/extra/zip.py
sprinko-0.1.0.dist-info/LICENSE
sprinko-0.1.0.dist-info/METADATA
sprinko-0.1.0.dist-info/WHEEL
sprinko-0.1.0.dist-info/entry_points.txt
sprinko-0.1.0.dist-info/top_level.txt
sprinko-0.1.0.dist-info/RECORD
