Metadata-Version: 2.1
Name: sprinko
Version: 0.1.0
Requires-Python: >=3.7
License-File: LICENSE
Requires-Dist: requests
Requires-Dist: click
Requires-Dist: orjson
Requires-Dist: parse
Requires-Dist: toml
Requires-Dist: tabulate
Requires-Dist: prompt-toolkit
